rekognition_jsonParser/__init__.py
rekognition_jsonParser/rekognition_jsonParser.py
rekognition_jsonParser_MatyasGreff-0.0.1.dist-info/LICENSE
rekognition_jsonParser_MatyasGreff-0.0.1.dist-info/METADATA
rekognition_jsonParser_MatyasGreff-0.0.1.dist-info/WHEEL
rekognition_jsonParser_MatyasGreff-0.0.1.dist-info/top_level.txt
rekognition_jsonParser_MatyasGreff-0.0.1.dist-info/RECORD
