Metadata-Version: 2.1
Name: rekognition-jsonParser-MatyasGreff
Version: 0.0.1
Summary: Takes response from AWS rekognition and pasres it into a 2D list
Home-page: https://github.com/pypa/sampleproject
Author: Matyas Greff
Author-email: matyas.greff1991@gmail.com
License: UNKNOWN
Project-URL: Bug Tracker, https://github.com/MatyasGreff/rekognition_jsonParser
Platform: UNKNOWN
Classifier: Programming Language :: Python :: 3
Classifier: License :: OSI Approved :: MIT License
Classifier: Operating System :: OS Independent
Requires-Python: >=3.7
License-File: LICENSE
